<?xml version="1.0" encoding="utf-8" ?>
<dwsync>
<file name="add_gray.svg" server="web01.nss-server.net/evolgear.com/" local="132602076000000000" remote="132602076000000000" Dst="0" />
<file name="add_icon.svg" server="web01.nss-server.net/evolgear.com/" local="132602940000000000" remote="132602940000000000" Dst="0" />
<file name="add_icon_02.svg" server="web01.nss-server.net/evolgear.com/" local="132602940000000000" remote="132602940000000000" Dst="0" />
<file name="remove_icon.svg" server="web01.nss-server.net/evolgear.com/" local="132602940000000000" remote="132602940000000000" Dst="0" />
<file name="plus_icon.svg" server="web01.nss-server.net/evolgear.com/" local="132602940000000000" remote="132602940000000000" Dst="0" />
<file name="bg_patterns.svg" server="web01.nss-server.net/evolgear.com/" local="132602940000000000" remote="132602940000000000" Dst="0" />
<file name="upload_icon.svg" server="web01.nss-server.net/evolgear.com/" local="132602940000000000" remote="132602940000000000" Dst="0" />
<file name="subtraction_icon.svg" server="web01.nss-server.net/evolgear.com/" local="132604668000000000" remote="132604668000000000" Dst="0" />
<file name="back_icon.svg" server="web01.nss-server.net/evolgear.com/" local="132608124000000000" remote="132608124000000000" Dst="0" />
<file name="complete_icon.svg" server="web01.nss-server.net/evolgear.com/" local="132608124000000000" remote="132608124000000000" Dst="0" />
<file name="change-icon.svg" server="web01.nss-server.net/evolgear.com/" local="132702300000000000" remote="132702300000000000" Dst="0" />
<file name="garbage-icon.svg" server="web01.nss-server.net/evolgear.com/" local="132702300000000000" remote="132702300000000000" Dst="0" />
<file name="plus-icon.svg" server="web01.nss-server.net/evolgear.com/" local="132702300000000000" remote="132702300000000000" Dst="0" />
<file name="list_icon.svg" server="web01.nss-server.net/evolgear.com/" local="132672060000000000" remote="132672060000000000" Dst="0" />
<file name="check_icon.svg" server="web01.nss-server.net/evolgear.com/" local="132675516000000000" remote="132675516000000000" Dst="0" />
<file name="update_icon.svg" server="web01.nss-server.net/evolgear.com/" local="132686748000000000" remote="132686748000000000" Dst="0" />
<file name="add_case_icon.svg" server="web01.nss-server.net/evolgear.com/" local="132702300000000000" remote="132702300000000000" Dst="0" />
<file name="delivery_icon.svg" server="web01.nss-server.net/evolgear.com/" local="132702300000000000" remote="132702300000000000" Dst="0" />
<file name="is_unview_icon.svg" server="web01.nss-server.net/evolgear.com/" local="132707484000000000" remote="132707484000000000" Dst="0" />
<file name="is_view_icon.svg" server="web01.nss-server.net/evolgear.com/" local="132702300000000000" remote="132702300000000000" Dst="0" />
<file name="list_case_icon.svg" server="web01.nss-server.net/evolgear.com/" local="132702300000000000" remote="132702300000000000" Dst="0" />
<file name="modified_by_icon.svg" server="web01.nss-server.net/evolgear.com/" local="132702300000000000" remote="132702300000000000" Dst="0" />
<file name="modified_date_icon.svg" server="web01.nss-server.net/evolgear.com/" local="132702300000000000" remote="132702300000000000" Dst="0" />
<file name="bk_login_image.jpeg" server="web01.nss-server.net/evolgear.com/" local="132707484000000000" remote="132707484000000000" Dst="0" />
<file name="main_logo_icon.svg" server="web01.nss-server.net/evolgear.com/" local="132707484000000000" remote="132707484000000000" Dst="0" />
<file name="sort_icon.svg" server="web01.nss-server.net/evolgear.com/" local="132836016680671660" remote="132839340000000000" Dst="0" />
<file name="outlet_icon.svg" server="web01.nss-server.net/evolgear.com/" local="132917075628360346" remote="132917938800000000" Dst="0" />
<file name="mark_position.png" server="web01.nss-server.net/evolgear.com/" local="132937071893966027" remote="132941120400000000" Dst="0" />
<file name="stamp.png" server="web01.nss-server.net/evolgear.com/" local="132935324970713852" remote="132941120400000000" Dst="0" />
<file name="title_copy_estimate.svg" server="web01.nss-server.net/evolgear.com/" local="132938815517888407" remote="132941120400000000" Dst="0" />
<file name="title_create_new_estimate.svg" server="web01.nss-server.net/evolgear.com/" local="132938812489065087" remote="132941120400000000" Dst="0" />
<file name="title_create_new_order.svg" server="web01.nss-server.net/evolgear.com/" local="132938817243539667" remote="132941120400000000" Dst="0" />
<file name="title_estimate_list.svg" server="web01.nss-server.net/evolgear.com/" local="132938809405090400" remote="132941120400000000" Dst="0" />
<file name="title_order_completed.svg" server="web01.nss-server.net/evolgear.com/" local="132938818894139408" remote="132941120400000000" Dst="0" />
<file name="title_update_estimate.svg" server="web01.nss-server.net/evolgear.com/" local="132938814458687017" remote="132941120400000000" Dst="0" />
</dwsync>